[
  {
    "source": "kasacja",
    "target": "langer-axis-kasacja",
    "type": "crossover",
    "certainty": 100,
    "importance": "major",
    "pathType": "straight",
    "sourceHandle": "source-bottom",
    "targetHandle": "target-top",
    "characters": ["piotr-langer"],
    "note": "Piotr Langer jest głównym klientem Joanny Chyłki i Kordiana Oryńskiego, oskarżonym o brutalne morderstwo dwóch osób, z których zwłokami przebywał w mieszkaniu przez dziesięć dni. Przyjmuje postawę milczenia i apatii, co początkowo sugeruje chorobę psychiczną, jednak ostatecznie przed sądem stanowczo zaprzecza swojej niepoczytalności. Udział Langera opiera się na genialnej manipulacji systemem prawnym i własnymi obrońcami: zza krat steruje procesem, nadając ukryte wiadomości alfabetem Morse’a za pomocą mrugania powiekami. Wiadomości te prowadzą prawników do Siwowłosego oraz grobu Antoniego Wansela, co staje się kluczowe dla podważenia ustaleń faktycznych i ostatecznego uniewinnienia go przez Sąd Najwyższy. Finał ujawnia, że Langer faktycznie dokonał zbrodni, a cały proces i rzekomy spisek mafii były zaplanowaną mistyfikacją."
  },
  {
    "source": "werdykt",
    "target": "widmo-brockenu",
    "type": "kontynuacja",
    "certainty": 100,
    "importance": "major",
    "characters": ["joanna-chylka", "kordian-orynski"],
    "note": "Chyłka jedzie w Tatry, Forst pojawia się w Afekcie, a w Widmie Brockenu oboje prowadzą pełnoprawne wspólne śledztwo."
  },
  {
    "source": "urwisko",
    "target": "arachnia",
    "type": "wzmianka",
    "certainty": 100,
    "importance": "finale",
    "pathType": "straight",
    "sourceHandle": "source-bottom",
    "targetHandle": "target-top",
    "note": "Urwisko i Arachnia dzieją się w tym samym czasie: w Warszawie ważą się losy Langera, a na Podhalu Forst walczy o przetrwanie."
  }
]